fmbf/__init__.py
fmbf-1.2.2.dist-info/METADATA
fmbf-1.2.2.dist-info/WHEEL
fmbf-1.2.2.dist-info/licenses/LICENSE
fmbf-1.2.2.dist-info/RECORD
