Metadata-Version: 2.3
Name: fmbf
Version: 1.2.2
Summary: Fork's Minecraft Botting Framework
Project-URL: Homepage, https://github.com/vpgel/fmbf
Project-URL: Issues, https://github.com/vpgel/fmbf/issues
Author-email: Fork Genesis <vasyapinfo@ya.ru>
Classifier: License :: OSI Approved :: MIT License
Classifier: Operating System :: OS Independent
Classifier: Programming Language :: Python :: 3
Requires-Python: >=3.12
